hc_mcp_api_docs/__init__.py
hc_mcp_api_docs/server.py
hc_mcp_api_docs-2025.2.1.dist-info/METADATA
hc_mcp_api_docs-2025.2.1.dist-info/WHEEL
hc_mcp_api_docs-2025.2.1.dist-info/entry_points.txt
hc_mcp_api_docs-2025.2.1.dist-info/RECORD
