Metadata-Version: 2.4
Name: hc-mcp-api-docs
Version: 2025.2.1
Summary: MCP server for our API documentation
Author-email: Erik Meinders <erik@easytocloud.com>
Requires-Python: >=3.10
Requires-Dist: httpx>=0.28.1
Requires-Dist: mcp>=1.2.1
Requires-Dist: pydantic>=2.10.6
